onepassword_secrets.py
1password_secrets-0.3.0.dist-info/METADATA
1password_secrets-0.3.0.dist-info/WHEEL
1password_secrets-0.3.0.dist-info/entry_points.txt
1password_secrets-0.3.0.dist-info/top_level.txt
1password_secrets-0.3.0.dist-info/RECORD
