Metadata-Version: 2.4
Name: 1password-secrets
Version: 0.3.0
Summary: 1password-secrets is a set of utilities to sync 1password secrets.
Home-page: https://github.com/significa/fly-1password-secrets
Author: Significa
License: MIT
Keywords: fly.io,1password,secrets
Classifier: Development Status :: 4 - Beta
Classifier: Environment :: Console
Classifier: Intended Audience :: Developers
Classifier: License :: OSI Approved :: MIT License
Classifier: Topic :: Utilities
Classifier: Programming Language :: Python :: 3
Classifier: Programming Language :: Python :: 3.10
Classifier: Programming Language :: Python :: 3.11
Classifier: Programming Language :: Python :: 3.12
Classifier: Programming Language :: Python :: 3.13
Classifier: Programming Language :: Python :: 3.14
Requires-Python: >=3.10
Requires-Dist: python-dotenv==1.2.1
Requires-Dist: sgqlc==17.1
Dynamic: author
Dynamic: classifier
Dynamic: description
Dynamic: description-content-type
Dynamic: home-page
Dynamic: keywords
Dynamic: license
Dynamic: requires-dist
Dynamic: requires-python
Dynamic: summary
